srtfu/__init__.py
srtfu/funcs.py
srtfu/libsrt.py
srtfu/libsrtinstall.py
srtfu/srtfu.py
srtfu/version.py
srtfu-0.0.11.dist-info/licenses/LICENSE
srtfu-0.0.11.dist-info/METADATA
srtfu-0.0.11.dist-info/WHEEL
srtfu-0.0.11.dist-info/top_level.txt
srtfu-0.0.11.dist-info/RECORD
