Metadata-Version: 2.4
Name: SRTfu
Version: 0.0.11
Summary: Secure Reliable Transport
Home-page: https://github.com/superkabuki/SRTfu
Author: Adrian of Doom 
Author-email: spam@bad.show
Classifier: License :: OSI Approved :: Sleepycat License
Classifier: Environment :: Console
Classifier: Natural Language :: English
Classifier: Operating System :: OS Independent
Classifier: Operating System :: Unix
Classifier: Operating System :: Other OS
Classifier: Operating System :: POSIX :: BSD :: OpenBSD
Classifier: Operating System :: POSIX :: BSD :: NetBSD
Classifier: Operating System :: POSIX :: Linux
Classifier: Operating System :: POSIX :: SCO
Classifier: Topic :: Multimedia :: Video
Classifier: Programming Language :: Python :: 3.9
Classifier: Programming Language :: Python :: 3.10
Classifier: Programming Language :: Python :: 3.11
Classifier: Programming Language :: Python :: 3.12
Classifier: Programming Language :: Python :: Implementation :: PyPy
Classifier: Programming Language :: Python :: Implementation :: CPython
Requires-Python: >=3.9
License-File: LICENSE
Dynamic: author
Dynamic: author-email
Dynamic: classifier
Dynamic: description
Dynamic: description-content-type
Dynamic: home-page
Dynamic: license-file
Dynamic: requires-python
Dynamic: summary
